[
  {
    "timestamp": 1759520640.0,
    "open": 122764.29,
    "high": 122786.0,
    "low": 122572.78,
    "close": 122642.57,
    "volume": 122.76110999999999,
    "index": 0
  },
  {
    "timestamp": 1759521540.0,
    "open": 122642.58,
    "high": 122695.6,
    "low": 122037.43,
    "close": 122057.19,
    "volume": 169.40013,
    "index": 1
  },
  {
    "timestamp": 1759522440.0,
    "open": 122057.2,
    "high": 122307.18,
    "low": 122057.19,
    "close": 122111.64,
    "volume": 188.88146,
    "index": 2
  },
  {
    "timestamp": 1759523340.0,
    "open": 122111.64,
    "high": 122602.98,
    "low": 122111.64,
    "close": 122595.84,
    "volume": 151.75968999999998,
    "index": 3
  },
  {
    "timestamp": 1759524240.0,
    "open": 122595.85,
    "high": 122734.92,
    "low": 122489.64,
    "close": 122502.98,
    "volume": 109.84628000000001,
    "index": 4
  },
  {
    "timestamp": 1759525140.0,
    "open": 122502.98,
    "high": 122502.99,
    "low": 122367.97,
    "close": 122374.09,
    "volume": 78.82239999999999,
    "index": 5
  },
  {
    "timestamp": 1759526040.0,
    "open": 122374.1,
    "high": 122451.82,
    "low": 122276.5,
    "close": 122291.65,
    "volume": 82.5224,
    "index": 6
  },
  {
    "timestamp": 1759526940.0,
    "open": 122291.65,
    "high": 122357.02,
    "low": 122063.68,
    "close": 122124.0,
    "volume": 104.05335,
    "index": 7
  },
  {
    "timestamp": 1759527840.0,
    "open": 122124.0,
    "high": 122403.85,
    "low": 121999.33,
    "close": 122364.57,
    "volume": 129.24668,
    "index": 8
  },
  {
    "timestamp": 1759528740.0,
    "open": 122364.57,
    "high": 122449.37,
    "low": 122306.56,
    "close": 122427.34,
    "volume": 64.00752,
    "index": 9
  },
  {
    "timestamp": 1759529640.0,
    "open": 122427.34,
    "high": 122534.23,
    "low": 122427.33,
    "close": 122481.13,
    "volume": 46.99631999999999,
    "index": 10
  },
  {
    "timestamp": 1759530540.0,
    "open": 122481.13,
    "high": 122665.0,
    "low": 122481.13,
    "close": 122585.06,
    "volume": 78.14436,
    "index": 11
  },
  {
    "timestamp": 1759531440.0,
    "open": 122585.07,
    "high": 122598.0,
    "low": 122447.83,
    "close": 122470.01,
    "volume": 40.873259999999995,
    "index": 12
  },
  {
    "timestamp": 1759532340.0,
    "open": 122470.01,
    "high": 122477.0,
    "low": 122283.01,
    "close": 122291.48,
    "volume": 100.51628,
    "index": 13
  },
  {
    "timestamp": 1759533240.0,
    "open": 122291.49,
    "high": 122358.43,
    "low": 122283.0,
    "close": 122299.69,
    "volume": 50.30596,
    "index": 14
  },
  {
    "timestamp": 1759534140.0,
    "open": 122299.7,
    "high": 122332.68,
    "low": 122196.69,
    "close": 122329.29,
    "volume": 53.62198999999999,
    "index": 15
  },
  {
    "timestamp": 1759535040.0,
    "open": 122329.29,
    "high": 122329.29,
    "low": 122180.79,
    "close": 122206.07,
    "volume": 85.94393,
    "index": 16
  },
  {
    "timestamp": 1759535940.0,
    "open": 122206.06,
    "high": 122260.0,
    "low": 122060.18,
    "close": 122199.99,
    "volume": 126.51179000000002,
    "index": 17
  },
  {
    "timestamp": 1759536840.0,
    "open": 122199.99,
    "high": 122295.56,
    "low": 122168.56,
    "close": 122198.17,
    "volume": 129.90535000000003,
    "index": 18
  },
  {
    "timestamp": 1759537740.0,
    "open": 122198.17,
    "high": 122198.18,
    "low": 121982.23,
    "close": 122043.79,
    "volume": 96.54072000000001,
    "index": 19
  },
  {
    "timestamp": 1759538640.0,
    "open": 122043.8,
    "high": 122094.0,
    "low": 121993.25,
    "close": 122081.5,
    "volume": 88.00014,
    "index": 20
  },
  {
    "timestamp": 1759539540.0,
    "open": 122081.5,
    "high": 122103.24,
    "low": 122020.0,
    "close": 122040.86,
    "volume": 73.78519,
    "index": 21
  },
  {
    "timestamp": 1759540440.0,
    "open": 122040.87,
    "high": 122095.0,
    "low": 121973.25,
    "close": 121973.25,
    "volume": 92.85728,
    "index": 22
  },
  {
    "timestamp": 1759541340.0,
    "open": 121973.25,
    "high": 122029.16,
    "low": 121866.86,
    "close": 121889.47,
    "volume": 183.8376,
    "index": 23
  },
  {
    "timestamp": 1759542240.0,
    "open": 121889.47,
    "high": 121901.67,
    "low": 121698.8,
    "close": 121793.99,
    "volume": 135.76840999999996,
    "index": 24
  },
  {
    "timestamp": 1759543140.0,
    "open": 121793.99,
    "high": 122030.0,
    "low": 121793.99,
    "close": 121895.34,
    "volume": 115.69037,
    "index": 25
  },
  {
    "timestamp": 1759544040.0,
    "open": 121895.34,
    "high": 121895.34,
    "low": 121685.71,
    "close": 121799.99,
    "volume": 152.34722999999997,
    "index": 26
  },
  {
    "timestamp": 1759544940.0,
    "open": 121800.0,
    "high": 121841.1,
    "low": 121684.97,
    "close": 121759.06,
    "volume": 78.17510000000001,
    "index": 27
  },
  {
    "timestamp": 1759545840.0,
    "open": 121759.07,
    "high": 121950.09,
    "low": 121724.0,
    "close": 121852.01,
    "volume": 96.11788000000001,
    "index": 28
  },
  {
    "timestamp": 1759546740.0,
    "open": 121852.0,
    "high": 121896.67,
    "low": 121825.5,
    "close": 121866.58,
    "volume": 75.11791999999998,
    "index": 29
  },
  {
    "timestamp": 1759547640.0,
    "open": 121866.58,
    "high": 122066.53,
    "low": 121866.57,
    "close": 122051.16,
    "volume": 85.85273,
    "index": 30
  },
  {
    "timestamp": 1759548540.0,
    "open": 122051.15,
    "high": 122098.69,
    "low": 122038.26,
    "close": 122093.77,
    "volume": 95.18277,
    "index": 31
  },
  {
    "timestamp": 1759549440.0,
    "open": 122093.76,
    "high": 122325.6,
    "low": 122038.28,
    "close": 122249.23,
    "volume": 101.57625999999999,
    "index": 32
  },
  {
    "timestamp": 1759550340.0,
    "open": 122249.23,
    "high": 122313.13,
    "low": 122221.0,
    "close": 122295.95,
    "volume": 91.73125000000002,
    "index": 33
  },
  {
    "timestamp": 1759551240.0,
    "open": 122295.96,
    "high": 122377.75,
    "low": 122219.3,
    "close": 122351.7,
    "volume": 77.23622,
    "index": 34
  },
  {
    "timestamp": 1759552140.0,
    "open": 122351.7,
    "high": 122500.0,
    "low": 122296.0,
    "close": 122480.15,
    "volume": 98.30324,
    "index": 35
  },
  {
    "timestamp": 1759553040.0,
    "open": 122480.15,
    "high": 122522.0,
    "low": 122454.54,
    "close": 122509.22,
    "volume": 51.574870000000004,
    "index": 36
  },
  {
    "timestamp": 1759553940.0,
    "open": 122509.23,
    "high": 122671.0,
    "low": 122442.72,
    "close": 122632.28,
    "volume": 112.87060000000001,
    "index": 37
  },
  {
    "timestamp": 1759554840.0,
    "open": 122632.29,
    "high": 122800.0,
    "low": 122620.0,
    "close": 122707.84,
    "volume": 110.1878,
    "index": 38
  },
  {
    "timestamp": 1759555740.0,
    "open": 122707.83,
    "high": 122718.08,
    "low": 122495.3,
    "close": 122495.31,
    "volume": 184.08758,
    "index": 39
  },
  {
    "timestamp": 1759556640.0,
    "open": 122495.31,
    "high": 122599.45,
    "low": 122405.64,
    "close": 122495.39,
    "volume": 183.90276,
    "index": 40
  },
  {
    "timestamp": 1759557540.0,
    "open": 122495.39,
    "high": 122560.34,
    "low": 122373.9,
    "close": 122387.75,
    "volume": 99.61940999999999,
    "index": 41
  },
  {
    "timestamp": 1759558440.0,
    "open": 122387.75,
    "high": 122606.86,
    "low": 122387.75,
    "close": 122507.45,
    "volume": 142.83449,
    "index": 42
  },
  {
    "timestamp": 1759559340.0,
    "open": 122507.45,
    "high": 122561.89,
    "low": 122488.5,
    "close": 122488.5,
    "volume": 68.72118999999999,
    "index": 43
  },
  {
    "timestamp": 1759560240.0,
    "open": 122488.51,
    "high": 122519.5,
    "low": 122437.63,
    "close": 122457.37,
    "volume": 50.02439999999999,
    "index": 44
  },
  {
    "timestamp": 1759561140.0,
    "open": 122457.37,
    "high": 122457.37,
    "low": 122348.6,
    "close": 122437.68,
    "volume": 74.24283,
    "index": 45
  },
  {
    "timestamp": 1759562040.0,
    "open": 122437.68,
    "high": 122437.68,
    "low": 122317.0,
    "close": 122345.55,
    "volume": 57.765730000000005,
    "index": 46
  },
  {
    "timestamp": 1759562940.0,
    "open": 122345.54,
    "high": 122393.02,
    "low": 122280.11,
    "close": 122301.35,
    "volume": 86.62351999999998,
    "index": 47
  },
  {
    "timestamp": 1759563840.0,
    "open": 122300.57,
    "high": 122342.87,
    "low": 122259.98,
    "close": 122342.86,
    "volume": 38.798739999999995,
    "index": 48
  },
  {
    "timestamp": 1759564740.0,
    "open": 122342.86,
    "high": 122539.83,
    "low": 122296.75,
    "close": 122539.83,
    "volume": 92.59851,
    "index": 49
  },
  {
    "timestamp": 1759565640.0,
    "open": 122539.82,
    "high": 122539.83,
    "low": 122362.83,
    "close": 122442.04,
    "volume": 248.8555,
    "index": 50
  },
  {
    "timestamp": 1759566540.0,
    "open": 122442.05,
    "high": 122442.05,
    "low": 122218.92,
    "close": 122218.92,
    "volume": 88.57226999999999,
    "index": 51
  },
  {
    "timestamp": 1759567440.0,
    "open": 122218.93,
    "high": 122321.82,
    "low": 122197.63,
    "close": 122280.51,
    "volume": 67.48629,
    "index": 52
  },
  {
    "timestamp": 1759568340.0,
    "open": 122280.52,
    "high": 122414.16,
    "low": 122267.57,
    "close": 122414.15,
    "volume": 95.76504,
    "index": 53
  },
  {
    "timestamp": 1759569240.0,
    "open": 122414.15,
    "high": 122457.17,
    "low": 122360.89,
    "close": 122380.0,
    "volume": 36.121269999999996,
    "index": 54
  },
  {
    "timestamp": 1759570140.0,
    "open": 122380.01,
    "high": 122380.01,
    "low": 122308.54,
    "close": 122327.81,
    "volume": 54.58886,
    "index": 55
  },
  {
    "timestamp": 1759571040.0,
    "open": 122327.81,
    "high": 122327.82,
    "low": 122186.03,
    "close": 122208.78,
    "volume": 60.72549,
    "index": 56
  },
  {
    "timestamp": 1759571940.0,
    "open": 122208.79,
    "high": 122273.32,
    "low": 122196.94,
    "close": 122228.99,
    "volume": 31.9458,
    "index": 57
  },
  {
    "timestamp": 1759572840.0,
    "open": 122229.0,
    "high": 122318.9,
    "low": 122218.0,
    "close": 122292.43,
    "volume": 52.096619999999994,
    "index": 58
  },
  {
    "timestamp": 1759573740.0,
    "open": 122292.44,
    "high": 122331.01,
    "low": 122200.0,
    "close": 122231.41,
    "volume": 39.13677,
    "index": 59
  },
  {
    "timestamp": 1759574640.0,
    "open": 122231.4,
    "high": 122237.0,
    "low": 122099.69,
    "close": 122129.54,
    "volume": 86.58618999999999,
    "index": 60
  },
  {
    "timestamp": 1759575540.0,
    "open": 122129.53,
    "high": 122215.97,
    "low": 122054.09,
    "close": 122054.1,
    "volume": 122.16159000000002,
    "index": 61
  },
  {
    "timestamp": 1759576440.0,
    "open": 122054.1,
    "high": 122129.0,
    "low": 121962.81,
    "close": 122097.21,
    "volume": 104.64960000000002,
    "index": 62
  },
  {
    "timestamp": 1759577340.0,
    "open": 122097.2,
    "high": 122134.53,
    "low": 122028.39,
    "close": 122082.0,
    "volume": 41.356849999999994,
    "index": 63
  },
  {
    "timestamp": 1759578240.0,
    "open": 122082.0,
    "high": 122082.01,
    "low": 122000.0,
    "close": 122000.01,
    "volume": 42.31211,
    "index": 64
  },
  {
    "timestamp": 1759579140.0,
    "open": 122000.0,
    "high": 122100.0,
    "low": 121973.25,
    "close": 122099.99,
    "volume": 51.47085,
    "index": 65
  },
  {
    "timestamp": 1759580040.0,
    "open": 122100.0,
    "high": 122103.0,
    "low": 122067.18,
    "close": 122067.19,
    "volume": 25.70893,
    "index": 66
  }
]